sign_language_translator/__init__.py
sign_language_translator/cli.py
sign_language_translator/config/__init__.py
sign_language_translator/config/assets.py
sign_language_translator/config/colors.py
sign_language_translator/config/enums.py
sign_language_translator/config/settings.py
sign_language_translator/config/urls.json
sign_language_translator/config/utils.py
sign_language_translator/languages/__init__.py
sign_language_translator/languages/sign/__init__.py
sign_language_translator/languages/sign/mapping_rules.py
sign_language_translator/languages/sign/pakistan_sign_language.py
sign_language_translator/languages/sign/sign_language.py
sign_language_translator/languages/text/__init__.py
sign_language_translator/languages/text/english.py
sign_language_translator/languages/text/hindi.py
sign_language_translator/languages/text/text_language.py
sign_language_translator/languages/text/urdu.py
sign_language_translator/languages/utils.py
sign_language_translator/languages/vocab.py
sign_language_translator/models/__init__.py
sign_language_translator/models/_utils.py
sign_language_translator/models/language_models/__init__.py
sign_language_translator/models/language_models/abstract_language_model.py
sign_language_translator/models/language_models/beam_sampling.py
sign_language_translator/models/language_models/mixer.py
sign_language_translator/models/language_models/ngram_language_model.py
sign_language_translator/models/language_models/transformer_language_model/__init__.py
sign_language_translator/models/language_models/transformer_language_model/layers.py
sign_language_translator/models/language_models/transformer_language_model/model.py
sign_language_translator/models/language_models/transformer_language_model/train.py
sign_language_translator/models/sign_to_text/__init__.py
sign_language_translator/models/text_embedding/__init__.py
sign_language_translator/models/text_embedding/text_embedding_model.py
sign_language_translator-0.8.1.dist-info/LICENSE
sign_language_translator-0.8.1.dist-info/METADATA
sign_language_translator-0.8.1.dist-info/WHEEL
sign_language_translator-0.8.1.dist-info/entry_points.txt
sign_language_translator-0.8.1.dist-info/RECORD
