Metadata-Version: 2.1
Name: sign_language_translator
Version: 0.8.1
Summary: Build custom Translators and Translate between text and sign language videos with AI.
Home-page: https://github.com/sign-language-translator/sign-language-translator
License: Apache-2.0
Keywords: sign-language,sign-language-translation,nlp,computer-vision,deep-learning,ai,translation,translator,sign-language-translator,rule-based
Author: Mudassar Iqbal
Author-email: mdsriqb@gmail.com
Requires-Python: >=3.8,<3.13
Classifier: License :: OSI Approved :: Apache Software License
Classifier: Programming Language :: Python :: 3
Classifier: Programming Language :: Python :: 3.8
Classifier: Programming Language :: Python :: 3.9
Classifier: Programming Language :: Python :: 3.10
Classifier: Programming Language :: Python :: 3.11
Provides-Extra: all
Provides-Extra: dev
Provides-Extra: full
Provides-Extra: mediapipe
Provides-Extra: synonyms
Requires-Dist: black (>=24.4.2,<25.0.0) ; extra == "dev"
Requires-Dist: click (>=8.1.4,<9.0.0)
Requires-Dist: deep-translator (>=1.11.4,<2.0.0) ; extra == "synonyms" or extra == "full" or extra == "all"
Requires-Dist: isort (>=5.13.2,<6.0.0) ; extra == "dev"
Requires-Dist: matplotlib (>=3.7.4,<4.0.0)
Requires-Dist: mediapipe (==0.10.9) ; (python_version >= "3.8" and python_full_version <= "3.11.0") and (extra == "mediapipe" or extra == "full" or extra == "all")
Requires-Dist: numpy (==1.24.4) ; python_version < "3.9"
Requires-Dist: numpy (==1.26.*) ; python_version >= "3.9" and python_version < "3.13"
Requires-Dist: opencv-contrib-python (>=4.8.0.74,<5.0.0.0)
Requires-Dist: pytest (>=8.3.1,<9.0.0) ; extra == "dev"
Requires-Dist: pytest-cov (>=5.0.0,<6.0.0) ; extra == "dev"
Requires-Dist: requests (>=2.31.0,<3.0.0)
Requires-Dist: torch (==2.2.*)
Requires-Dist: tqdm (>=4.65.0,<5.0.0)
Project-URL: Documentation, https://sign-language-translator.readthedocs.io/en/latest/
Project-URL: Repository, https://github.com/sign-language-translator/sign-language-translator
